Pairtree-0.8.1.data/scripts/ppath
Pairtree-0.8.1.dist-info/DESCRIPTION.rst
Pairtree-0.8.1.dist-info/METADATA
Pairtree-0.8.1.dist-info/RECORD
Pairtree-0.8.1.dist-info/WHEEL
Pairtree-0.8.1.dist-info/metadata.json
Pairtree-0.8.1.dist-info/top_level.txt
pairtree/__init__.py
pairtree/myutils.py
pairtree/pairtree_client.py
pairtree/pairtree_object.py
pairtree/pairtree_path.py
pairtree/pairtree_revlookup.py
pairtree/pairtree_store.py
pairtree/storage_exceptions.py
tests/__init__.py
tests/test_functional.py
tests/test_pairtree.py
