Metadata-Version: 2.0
Name: Pairtree
Version: 0.8.1
Summary: Pairtree FS implementation.
Home-page: http://packages.python.org/Pairtree/
Author: Ben O'Steen
Author-email: bosteen@gmail.com
License: http://www.apache.org/licenses/LICENSE-2.0
Platform: UNKNOWN
